python_rfid/__init__.py
python_rfid/byte_utils.py
python_rfid/debug_dump.py
python_rfid/errors.py
python_rfid/mfrc522.py
python_rfid/mifare_handler.py
python_rfid/pcd_common.py
python_rfid/picc_common.py
python_rfid/picc_handler.py
python_rfid/self_test_data.py
python_rfid-0.0.2.dist-info/METADATA
python_rfid-0.0.2.dist-info/WHEEL
python_rfid-0.0.2.dist-info/licenses/LICENSE
python_rfid-0.0.2.dist-info/RECORD
