Metadata-Version: 2.1
Name: python_rfid
Version: 0.0.2
Summary: A library for communicating with RFID cards using MFRC522.
Author-email: Tobias Wessels <wessels.tobias@arcor.de>
License-File: LICENSE
Keywords: MFRC522,RFID
Classifier: Development Status :: 3 - Alpha
Classifier: License :: OSI Approved :: MIT License
Classifier: Operating System :: Unix
Classifier: Programming Language :: Python :: 3
Requires-Python: >=3.7
Requires-Dist: gpiod==1.5.3
Requires-Dist: spidev==3.5
